django_sql_dashboard/__init__.py
django_sql_dashboard/admin.py
django_sql_dashboard/apps.py
django_sql_dashboard/models.py
django_sql_dashboard/urls.py
django_sql_dashboard/utils.py
django_sql_dashboard/views.py
django_sql_dashboard/migrations/0001_initial.py
django_sql_dashboard/migrations/0002_dashboard_permissions.py
django_sql_dashboard/migrations/0003_update_metadata.py
django_sql_dashboard/migrations/0004_add_description_help_text.py
django_sql_dashboard/migrations/__init__.py
django_sql_dashboard/templates/django_sql_dashboard/_css.html
django_sql_dashboard/templates/django_sql_dashboard/_script.html
django_sql_dashboard/templates/django_sql_dashboard/base.html
django_sql_dashboard/templates/django_sql_dashboard/dashboard.html
django_sql_dashboard/templates/django_sql_dashboard/saved_dashboard.html
django_sql_dashboard/templates/django_sql_dashboard/widgets/_base_widget.html
django_sql_dashboard/templates/django_sql_dashboard/widgets/bar_label-bar_quantity.html
django_sql_dashboard/templates/django_sql_dashboard/widgets/big_number-label.html
django_sql_dashboard/templates/django_sql_dashboard/widgets/completed_count-total_count.html
django_sql_dashboard/templates/django_sql_dashboard/widgets/default.html
django_sql_dashboard/templates/django_sql_dashboard/widgets/error.html
django_sql_dashboard/templates/django_sql_dashboard/widgets/html.html
django_sql_dashboard/templates/django_sql_dashboard/widgets/markdown.html
django_sql_dashboard/templates/django_sql_dashboard/widgets/wordcloud_count-wordcloud_word.html
django_sql_dashboard/templatetags/__init__.py
django_sql_dashboard/templatetags/django_sql_dashboard.py
django_sql_dashboard-1.2.dist-info/LICENSE
django_sql_dashboard-1.2.dist-info/METADATA
django_sql_dashboard-1.2.dist-info/WHEEL
django_sql_dashboard-1.2.dist-info/top_level.txt
django_sql_dashboard-1.2.dist-info/RECORD
