Metadata-Version: 2.1
Name: django-sql-dashboard
Version: 1.2
Summary: Django app for building dashboards using raw SQL queries
Home-page: https://github.com/simonw/django-sql-dashboard
Author: Simon Willison
License: Apache License, Version 2.0
Project-URL: Documentation, https://django-sql-dashboard.datasette.io/
Project-URL: Issues, https://github.com/simonw/django-sql-dashboard/issues
Project-URL: CI, https://github.com/simonw/django-sql-dashboard/actions
Project-URL: Changelog, https://github.com/simonw/django-sql-dashboard/releases
Requires-Python: >=3.6
License-File: LICENSE
Requires-Dist: Django >=3.0
Requires-Dist: markdown
Requires-Dist: bleach
Provides-Extra: test
Requires-Dist: black >=22.3.0 ; extra == 'test'
Requires-Dist: psycopg2 ; extra == 'test'
Requires-Dist: pytest ; extra == 'test'
Requires-Dist: pytest-django ==4.2.0 ; extra == 'test'
Requires-Dist: pytest-pythonpath ; extra == 'test'
Requires-Dist: dj-database-url ; extra == 'test'
Requires-Dist: testing.postgresql ; extra == 'test'
Requires-Dist: beautifulsoup4 ; extra == 'test'
Requires-Dist: html5lib ; extra == 'test'
